base64_random/__init__.py
base64_random/__main__.py
base64_random/gen.py
base64_random-1.0.0.dist-info/METADATA
base64_random-1.0.0.dist-info/WHEEL
base64_random-1.0.0.dist-info/entry_points.txt
base64_random-1.0.0.dist-info/licenses/LICENSE
base64_random-1.0.0.dist-info/RECORD
