Metadata-Version: 2.1
Name: base64_random
Version: 1.0.0
Summary: Generates an arbitrary length base 64 random number.
Project-URL: Homepage, https://github.com/speratus/base64_random
Project-URL: Repository, https://github.com/speratus/base64_random
Author-email: Andrew Luchuk <andrew.luchuk@outlook.com>
License: Copyright © 2023 Andrew Luchuk
License-File: LICENSE
Keywords: base64,numbers,random
Classifier: Intended Audience :: Developers
Classifier: License :: OSI Approved :: MIT License
Classifier: Programming Language :: Python :: 3.11
Classifier: Topic :: Software Development
Classifier: Topic :: Software Development :: Libraries
